dash_fcast/__init__.py
dash_fcast/series.py
dash_fcast/table.py
dash_fcast/utils.py
dash_fcast/distributions/__init__.py
dash_fcast/distributions/base.py
dash_fcast/distributions/moments.py
dash_fcast/distributions/table.py
dash_fcast/distributions/utils.py
dash_fcast-0.0.5.dist-info/LICENSE
dash_fcast-0.0.5.dist-info/METADATA
dash_fcast-0.0.5.dist-info/WHEEL
dash_fcast-0.0.5.dist-info/top_level.txt
dash_fcast-0.0.5.dist-info/RECORD
