Metadata-Version: 2.1
Name: dash-fcast
Version: 0.0.5
Summary: High-level API for creating forecasting dashboards.
Home-page: https://dsbowen.github.io/dash-fcast/
Author: Dillon Bowen
Author-email: dsbowen@wharton.upenn.edu
License: UNKNOWN
Platform: UNKNOWN
Classifier: Programming Language :: Python :: 3
Classifier: License :: OSI Approved :: MIT License
Classifier: Operating System :: OS Independent
Requires-Python: >=3.6
Requires-Dist: dash (>=1.16.0)
Requires-Dist: dash-bootstrap-components (>=0.10.6)
Requires-Dist: pandas (>=1.1.2)
Requires-Dist: smoother (>=0.0.5)
